{
  "generated_at": "2026-06-10T10:54:53.608662+00:00",
  "errors": [
    {
      "timestamp": "2026-06-10T10:54:53.608662+00:00",
      "model_id": "poco-f8-pro-12-512",
      "model_name": "POCO F8 Pro",
      "store_id": "mi-com",
      "store_name": "Mi.com Polska",
      "url": "https://www.mi.com/pl/product/poco-f8-pro/",
      "error_type": "source_disabled",
      "error_message": "source_disabled",
      "status": "source_disabled",
      "parser_name": "mi-com",
      "fetch_method": "requests",
      "http_status": null,
      "product_name": null,
      "extracted_price_raw": null
    },
    {
      "timestamp": "2026-06-10T10:54:53.608662+00:00",
      "model_id": "poco-f8-ultra-16-512",
      "model_name": "POCO F8 Ultra",
      "store_id": "mi-com",
      "store_name": "Mi.com Polska",
      "url": "https://www.mi.com/pl/product/poco-f8-ultra/",
      "error_type": "source_disabled",
      "error_message": "source_disabled",
      "status": "source_disabled",
      "parser_name": "mi-com",
      "fetch_method": "requests",
      "http_status": null,
      "product_name": null,
      "extracted_price_raw": null
    },
    {
      "timestamp": "2026-06-10T10:54:53.608662+00:00",
      "model_id": "poco-f7-ultra-16-512",
      "model_name": "POCO F7 Ultra",
      "store_id": "mi-com",
      "store_name": "Mi.com Polska",
      "url": "https://www.mi.com/pl/product/poco-f7-ultra/",
      "error_type": "source_disabled",
      "error_message": "source_disabled",
      "status": "source_disabled",
      "parser_name": "mi-com",
      "fetch_method": "requests",
      "http_status": null,
      "product_name": null,
      "extracted_price_raw": null
    },
    {
      "timestamp": "2026-06-10T10:54:53.608662+00:00",
      "model_id": "poco-f7-pro-12-512",
      "model_name": "POCO F7 Pro",
      "store_id": "mi-com",
      "store_name": "Mi.com Polska",
      "url": "https://www.mi.com/pl/product/poco-f7-pro/",
      "error_type": "source_disabled",
      "error_message": "source_disabled",
      "status": "source_disabled",
      "parser_name": "mi-com",
      "fetch_method": "requests",
      "http_status": null,
      "product_name": null,
      "extracted_price_raw": null
    },
    {
      "timestamp": "2026-06-10T10:54:53.608662+00:00",
      "model_id": "poco-f7-pro-12-512",
      "model_name": "POCO F7 Pro",
      "store_id": "rtv-euro-agd",
      "store_name": "RTV Euro AGD",
      "url": "https://www.euro.com.pl/telefony-komorkowe/poco-f7-pro-5g-12-512gb-6-67-120hz-50mpix-srebrny.bhtml",
      "error_type": "price_missing",
      "error_message": "price_missing",
      "status": "price_missing",
      "parser_name": "rtv-euro-agd",
      "fetch_method": "playwright",
      "http_status": 403,
      "product_name": "RTV Euro AGD - Blokada",
      "extracted_price_raw": null
    },
    {
      "timestamp": "2026-06-10T10:54:53.608662+00:00",
      "model_id": "poco-f7-12-512",
      "model_name": "POCO F7",
      "store_id": "mi-com",
      "store_name": "Mi.com Polska",
      "url": "https://www.mi.com/pl/product/poco-f7/",
      "error_type": "source_disabled",
      "error_message": "source_disabled",
      "status": "source_disabled",
      "parser_name": "mi-com",
      "fetch_method": "requests",
      "http_status": null,
      "product_name": null,
      "extracted_price_raw": null
    },
    {
      "timestamp": "2026-06-10T10:54:53.608662+00:00",
      "model_id": "poco-x7-pro-12-512",
      "model_name": "POCO X7 Pro",
      "store_id": "rtv-euro-agd",
      "store_name": "RTV Euro AGD",
      "url": "https://www.euro.com.pl/telefony-komorkowe/poco-x7-pro-5g-12-512gb-6-67-120hz-50mpix-zielony.bhtml",
      "error_type": "price_missing",
      "error_message": "price_missing",
      "status": "price_missing",
      "parser_name": "rtv-euro-agd",
      "fetch_method": "playwright",
      "http_status": 403,
      "product_name": "RTV Euro AGD - Blokada",
      "extracted_price_raw": null
    },
    {
      "timestamp": "2026-06-10T10:54:53.608662+00:00",
      "model_id": "poco-x7-pro-12-512",
      "model_name": "POCO X7 Pro",
      "store_id": "x-kom",
      "store_name": "x-kom",
      "url": "https://www.x-kom.pl/p/1306175-smartfon-telefon-xiaomi-poco-x7-pro-12-512gb-black.html",
      "error_type": "source_disabled",
      "error_message": "source_disabled",
      "status": "source_disabled",
      "parser_name": "x-kom",
      "fetch_method": "requests",
      "http_status": null,
      "product_name": null,
      "extracted_price_raw": null
    },
    {
      "timestamp": "2026-06-10T10:54:53.608662+00:00",
      "model_id": "oneplus-nord-4-12-256",
      "model_name": "OnePlus Nord 4",
      "store_id": "oneplus-pl",
      "store_name": "OnePlus.com/pl",
      "url": "https://www.oneplus.com/pl/oneplus-nord-4",
      "error_type": "source_disabled",
      "error_message": "source_disabled",
      "status": "source_disabled",
      "parser_name": "oneplus-pl",
      "fetch_method": "requests",
      "http_status": null,
      "product_name": null,
      "extracted_price_raw": null
    },
    {
      "timestamp": "2026-06-10T10:54:53.608662+00:00",
      "model_id": "poco-f6-pro-12-512",
      "model_name": "POCO F6 Pro",
      "store_id": "x-kom",
      "store_name": "x-kom",
      "url": "https://www.x-kom.pl/p/1246220-smartfon-telefon-xiaomi-poco-f6-pro-12gb-512gb-white.html",
      "error_type": "source_disabled",
      "error_message": "source_disabled",
      "status": "source_disabled",
      "parser_name": "x-kom",
      "fetch_method": "requests",
      "http_status": null,
      "product_name": null,
      "extracted_price_raw": null
    },
    {
      "timestamp": "2026-06-10T10:54:53.608662+00:00",
      "model_id": "poco-f6-12-512",
      "model_name": "POCO F6",
      "store_id": "mi-com",
      "store_name": "Mi.com Polska",
      "url": "https://www.mi.com/pl/product/poco-f6/",
      "error_type": "source_disabled",
      "error_message": "source_disabled",
      "status": "source_disabled",
      "parser_name": "mi-com",
      "fetch_method": "requests",
      "http_status": null,
      "product_name": null,
      "extracted_price_raw": null
    },
    {
      "timestamp": "2026-06-10T10:54:53.608662+00:00",
      "model_id": "realme-14-pro-plus-12-512",
      "model_name": "realme 14 Pro+",
      "store_id": "media-expert",
      "store_name": "Media Expert",
      "url": "https://www.mediaexpert.pl/smartfony-i-zegarki/smartfony/smartfon-realme-14-pro-12-gb-512-gb-5g-czarny",
      "error_type": "blocked_or_captcha",
      "error_message": "Anti-bot detected",
      "status": "blocked_or_captcha",
      "parser_name": "media-expert",
      "fetch_method": "playwright",
      "http_status": 403,
      "product_name": null,
      "extracted_price_raw": null
    },
    {
      "timestamp": "2026-06-10T10:54:53.608662+00:00",
      "model_id": "realme-14-pro-plus-12-512",
      "model_name": "realme 14 Pro+",
      "store_id": "rtv-euro-agd",
      "store_name": "RTV Euro AGD",
      "url": "https://www.euro.com.pl/telefony-komorkowe/realme-14-pro-plus-5g-12-512gb-6-83-120hz-50mpix-szary.bhtml",
      "error_type": "price_missing",
      "error_message": "price_missing",
      "status": "price_missing",
      "parser_name": "rtv-euro-agd",
      "fetch_method": "playwright",
      "http_status": 403,
      "product_name": "RTV Euro AGD - Blokada",
      "extracted_price_raw": null
    },
    {
      "timestamp": "2026-06-10T10:54:53.608662+00:00",
      "model_id": "xiaomi-13t-8-256",
      "model_name": "Xiaomi 13T",
      "store_id": "rtv-euro-agd",
      "store_name": "RTV Euro AGD",
      "url": "https://www.euro.com.pl/telefony-komorkowe/xiaomi-13t-8-256gb-6-67-50-mpix-niebieski.bhtml",
      "error_type": "price_missing",
      "error_message": "price_missing",
      "status": "price_missing",
      "parser_name": "rtv-euro-agd",
      "fetch_method": "playwright",
      "http_status": 403,
      "product_name": "RTV Euro AGD - Blokada",
      "extracted_price_raw": null
    },
    {
      "timestamp": "2026-06-10T10:54:53.608662+00:00",
      "model_id": "xiaomi-13t-8-256",
      "model_name": "Xiaomi 13T",
      "store_id": "x-kom",
      "store_name": "x-kom",
      "url": "https://www.x-kom.pl/p/1179168-smartfon-telefon-xiaomi-13t-8-256gb-black.html",
      "error_type": "source_disabled",
      "error_message": "source_disabled",
      "status": "source_disabled",
      "parser_name": "x-kom",
      "fetch_method": "requests",
      "http_status": null,
      "product_name": null,
      "extracted_price_raw": null
    },
    {
      "timestamp": "2026-06-10T10:54:53.608662+00:00",
      "model_id": "samsung-galaxy-a56-8-256",
      "model_name": "Samsung Galaxy A56",
      "store_id": "rtv-euro-agd",
      "store_name": "RTV Euro AGD",
      "url": "https://www.euro.com.pl/telefony-komorkowe/samsung-galaxy-a56-5g-8-256gb-6-7-120hz-50mpix-sm-a566-grafitowy.bhtml",
      "error_type": "price_missing",
      "error_message": "price_missing",
      "status": "price_missing",
      "parser_name": "rtv-euro-agd",
      "fetch_method": "playwright",
      "http_status": 403,
      "product_name": "RTV Euro AGD - Blokada",
      "extracted_price_raw": null
    },
    {
      "timestamp": "2026-06-10T10:54:53.608662+00:00",
      "model_id": "samsung-galaxy-a56-8-256",
      "model_name": "Samsung Galaxy A56",
      "store_id": "samsung-pl",
      "store_name": "Samsung.com/pl",
      "url": "https://www.samsung.com/pl/smartphones/galaxy-a/galaxy-a56-5g-awesome-graphite-256gb-sm-a566bzkeeee/",
      "error_type": "source_disabled",
      "error_message": "source_disabled",
      "status": "source_disabled",
      "parser_name": "samsung-pl",
      "fetch_method": "requests",
      "http_status": null,
      "product_name": null,
      "extracted_price_raw": null
    },
    {
      "timestamp": "2026-06-10T10:54:53.608662+00:00",
      "model_id": "nothing-phone-3a-12-256",
      "model_name": "Nothing Phone (3a)",
      "store_id": "nothing-pl",
      "store_name": "Nothing.tech PL",
      "url": "https://nothing.tech/products/phone-3a",
      "error_type": "source_disabled",
      "error_message": "source_disabled",
      "status": "source_disabled",
      "parser_name": "nothing-pl",
      "fetch_method": "requests",
      "http_status": null,
      "product_name": null,
      "extracted_price_raw": null
    },
    {
      "timestamp": "2026-06-10T10:54:53.608662+00:00",
      "model_id": "redmi-note-14-pro-plus-5g-12-512",
      "model_name": "Redmi Note 14 Pro+ 5G",
      "store_id": "mi-com",
      "store_name": "Mi.com Polska",
      "url": "https://www.mi.com/pl/product/redmi-note-14-pro-plus-5g/",
      "error_type": "source_disabled",
      "error_message": "source_disabled",
      "status": "source_disabled",
      "parser_name": "mi-com",
      "fetch_method": "requests",
      "http_status": null,
      "product_name": null,
      "extracted_price_raw": null
    },
    {
      "timestamp": "2026-06-10T10:54:53.608662+00:00",
      "model_id": "redmi-note-14-pro-plus-5g-12-512",
      "model_name": "Redmi Note 14 Pro+ 5G",
      "store_id": "media-expert",
      "store_name": "Media Expert",
      "url": "https://www.mediaexpert.pl/smartfony-i-zegarki/smartfony/smartfon-xiaomi-redmi-note-14-pro-5g-12-512gb-6-67-120hz-czarny",
      "error_type": "blocked_or_captcha",
      "error_message": "Anti-bot detected",
      "status": "blocked_or_captcha",
      "parser_name": "media-expert",
      "fetch_method": "playwright",
      "http_status": 403,
      "product_name": null,
      "extracted_price_raw": null
    },
    {
      "timestamp": "2026-06-10T10:54:53.608662+00:00",
      "model_id": "redmi-note-14-pro-plus-5g-12-512",
      "model_name": "Redmi Note 14 Pro+ 5G",
      "store_id": "rtv-euro-agd",
      "store_name": "RTV Euro AGD",
      "url": "https://www.euro.com.pl/telefony-komorkowe/xiaomi-redmi-note-14-pro-5g-12-512gb-6-67-120hz-108mpix-czarny.bhtml",
      "error_type": "price_missing",
      "error_message": "price_missing",
      "status": "price_missing",
      "parser_name": "rtv-euro-agd",
      "fetch_method": "playwright",
      "http_status": 403,
      "product_name": "RTV Euro AGD - Blokada",
      "extracted_price_raw": null
    },
    {
      "timestamp": "2026-06-10T10:54:53.608662+00:00",
      "model_id": "motorola-edge-50-neo-12-512",
      "model_name": "Motorola Edge 50 Neo",
      "store_id": "media-expert",
      "store_name": "Media Expert",
      "url": "https://www.mediaexpert.pl/smartfony-i-zegarki/smartfony/smartfon-motorola-edge-50-neo-5g-12-512gb-6-4-120hz-granatowy",
      "error_type": "blocked_or_captcha",
      "error_message": "Anti-bot detected",
      "status": "blocked_or_captcha",
      "parser_name": "media-expert",
      "fetch_method": "playwright",
      "http_status": 403,
      "product_name": null,
      "extracted_price_raw": null
    },
    {
      "timestamp": "2026-06-10T10:54:53.608662+00:00",
      "model_id": "motorola-edge-50-neo-12-512",
      "model_name": "Motorola Edge 50 Neo",
      "store_id": "rtv-euro-agd",
      "store_name": "RTV Euro AGD",
      "url": "https://www.euro.com.pl/telefony-komorkowe/motorola-edge-50-neo-12-512gb-6-36-120hz-50mpix-stalowy.bhtml",
      "error_type": "price_missing",
      "error_message": "price_missing",
      "status": "price_missing",
      "parser_name": "rtv-euro-agd",
      "fetch_method": "playwright",
      "http_status": 403,
      "product_name": "RTV Euro AGD - Blokada",
      "extracted_price_raw": null
    },
    {
      "timestamp": "2026-06-10T10:54:53.608662+00:00",
      "model_id": "poco-x7-12-512",
      "model_name": "POCO X7",
      "store_id": "mi-com",
      "store_name": "Mi.com Polska",
      "url": "https://www.mi.com/pl/product/poco-x7/",
      "error_type": "source_disabled",
      "error_message": "source_disabled",
      "status": "source_disabled",
      "parser_name": "mi-com",
      "fetch_method": "requests",
      "http_status": null,
      "product_name": null,
      "extracted_price_raw": null
    },
    {
      "timestamp": "2026-06-10T10:54:53.608662+00:00",
      "model_id": "poco-x7-12-512",
      "model_name": "POCO X7",
      "store_id": "rtv-euro-agd",
      "store_name": "RTV Euro AGD",
      "url": "https://www.euro.com.pl/telefony-komorkowe/poco-x7-5g-12-512gb-6-67-120hz-50mpix-czarny-.bhtml",
      "error_type": "price_missing",
      "error_message": "price_missing",
      "status": "price_missing",
      "parser_name": "rtv-euro-agd",
      "fetch_method": "playwright",
      "http_status": 403,
      "product_name": "RTV Euro AGD - Blokada",
      "extracted_price_raw": null
    }
  ]
}
